cbujo/__init__.py
cbujo/cbujo.py
cbujo-0.0.2.dist-info/LICENSE
cbujo-0.0.2.dist-info/METADATA
cbujo-0.0.2.dist-info/WHEEL
cbujo-0.0.2.dist-info/RECORD
